{
    "date": "20230518",
    "geojson": "contents/20230518/history.json",
    "movement": {
        "walking": 7.9,
        "bus": 0,
        "train": 43.1,
        "airplane": 0,
        "subway": 0,
        "taxi": 0
    },
    "medias": [
        {
            "original": "contents/20230518/original/IMG_2617.avif",
            "thumbnail": "contents/20230518/thumbnail/IMG_2617.avif",
            "desc": "도치기역으로 이동하는중..",
            "latitude": 36.376647222222225,
            "longitude": 139.73010277777777,
            "model": "iPhone 14 Pro Max back triple camera 6.86mm f/1.78",
            "make": "Apple",
            "time": "2023-05-18T09:07:58.000Z"
        },
        {
            "original": "contents/20230518/original/IMG_2618.avif",
            "thumbnail": "contents/20230518/thumbnail/IMG_2618.avif",
            "desc": "단 하나뿐인 자신을, 단 하나밖에 없는 일생을, 정말로 즐기지 않는다면 태어난 보람이 없지 않는가. 라는 문구가 쓰여있는 다리 옆 조형물",
            "latitude": 36.37656388888889,
            "longitude": 139.73008611111112,
            "model": "iPhone 14 Pro Max back triple camera 6.86mm f/1.78",
            "make": "Apple",
            "time": "2023-05-18T09:08:35.000Z"
        },
        {
            "original": "contents/20230518/original/IMG_2619.avif",
            "thumbnail": "contents/20230518/thumbnail/IMG_2619.avif",
            "desc": "",
            "latitude": 36.315013888888885,
            "longitude": 139.51841666666667,
            "model": "iPhone 14 Pro Max back triple camera 6.86mm f/1.78",
            "make": "Apple",
            "time": "2023-05-18T10:07:30.000Z"
        },
        {
            "original": "contents/20230518/original/IMG_2622.avif",
            "thumbnail": "contents/20230518/thumbnail/IMG_2622.avif",
            "desc": "오늘의 목적지중 하나인 아시카가플라워파크에 도착",
            "latitude": 36.31505555555555,
            "longitude": 139.5220027777778,
            "model": "iPhone 14 Pro Max back triple camera 6.86mm f/1.78",
            "make": "Apple",
            "time": "2023-05-18T10:17:25.000Z"
        },
        {
            "original": "contents/20230518/original/IMG_2624.avif",
            "thumbnail": "contents/20230518/thumbnail/IMG_2624.avif",
            "desc": "",
            "latitude": 36.31494166666666,
            "longitude": 139.5215611111111,
            "model": "iPhone 14 Pro Max back triple camera 6.86mm f/1.78",
            "make": "Apple",
            "time": "2023-05-18T10:19:34.000Z"
        },
        {
            "original": "contents/20230518/original/IMG_2625.avif",
            "thumbnail": "contents/20230518/thumbnail/IMG_2625.avif",
            "desc": "",
            "latitude": 36.31464444444444,
            "longitude": 139.5217888888889,
            "model": "iPhone 14 Pro Max back triple camera 6.86mm f/1.78",
            "make": "Apple",
            "time": "2023-05-18T10:21:27.000Z"
        },
        {
            "original": "contents/20230518/original/IMG_2626.avif",
            "thumbnail": "contents/20230518/thumbnail/IMG_2626.avif",
            "desc": "",
            "latitude": 36.31468611111111,
            "longitude": 139.52183611111113,
            "model": "iPhone 14 Pro Max back triple camera 6.86mm f/1.78",
            "make": "Apple",
            "time": "2023-05-18T10:22:20.000Z"
        },
        {
            "original": "contents/20230518/original/IMG_2628.avif",
            "thumbnail": "contents/20230518/thumbnail/IMG_2628.avif",
            "desc": "",
            "latitude": 36.31456111111111,
            "longitude": 139.52191111111114,
            "model": "iPhone 14 Pro Max back triple camera 6.86mm f/1.78",
            "make": "Apple",
            "time": "2023-05-18T10:23:26.000Z"
        },
        {
            "original": "contents/20230518/original/IMG_2629.avif",
            "thumbnail": "contents/20230518/thumbnail/IMG_2629.avif",
            "desc": "",
            "latitude": 36.314616666666666,
            "longitude": 139.5216527777778,
            "model": "iPhone 14 Pro Max back triple camera 6.86mm f/1.78",
            "make": "Apple",
            "time": "2023-05-18T10:24:24.000Z"
        },
        {
            "original": "contents/20230518/original/IMG_2631.avif",
            "thumbnail": "contents/20230518/thumbnail/IMG_2631.avif",
            "desc": "",
            "latitude": 36.31460555555555,
            "longitude": 139.52146944444445,
            "model": "iPhone 14 Pro Max back triple camera 6.86mm f/1.78",
            "make": "Apple",
            "time": "2023-05-18T10:28:39.000Z"
        },
        {
            "original": "contents/20230518/original/IMG_2632.avif",
            "thumbnail": "contents/20230518/thumbnail/IMG_2632.avif",
            "desc": "",
            "latitude": 36.314563888888884,
            "longitude": 139.52122500000002,
            "model": "iPhone 14 Pro Max back triple camera 6.86mm f/1.78",
            "make": "Apple",
            "time": "2023-05-18T10:30:43.000Z"
        },
        {
            "original": "contents/20230518/original/IMG_2633.avif",
            "thumbnail": "contents/20230518/thumbnail/IMG_2633.avif",
            "desc": "",
            "latitude": 36.31460555555555,
            "longitude": 139.52120833333333,
            "model": "iPhone 14 Pro Max back triple camera 6.86mm f/1.78",
            "make": "Apple",
            "time": "2023-05-18T10:31:07.000Z"
        },
        {
            "original": "contents/20230518/original/IMG_2634.avif",
            "thumbnail": "contents/20230518/thumbnail/IMG_2634.avif",
            "desc": "",
            "latitude": 36.31458333333333,
            "longitude": 139.52122500000002,
            "model": "iPhone 14 Pro Max back dual wide camera 6.86mm f/1.78",
            "make": "Apple",
            "time": "2023-05-18T10:31:55.000Z"
        },
        {
            "original": "contents/20230518/original/IMG_2635.avif",
            "thumbnail": "contents/20230518/thumbnail/IMG_2635.avif",
            "desc": "",
            "latitude": 36.31455555555555,
            "longitude": 139.52125555555557,
            "model": "iPhone 14 Pro Max back dual wide camera 6.86mm f/1.78",
            "make": "Apple",
            "time": "2023-05-18T10:32:24.000Z"
        },
        {
            "original": "contents/20230518/original/IMG_2636.avif",
            "thumbnail": "contents/20230518/thumbnail/IMG_2636.avif",
            "desc": "",
            "latitude": 36.31454166666666,
            "longitude": 139.52101111111114,
            "model": "iPhone 14 Pro Max back dual wide camera 6.86mm f/1.78",
            "make": "Apple",
            "time": "2023-05-18T10:33:15.000Z"
        },
        {
            "original": "contents/20230518/original/IMG_2637.avif",
            "thumbnail": "contents/20230518/thumbnail/IMG_2637.avif",
            "desc": "",
            "latitude": 36.314449999999994,
            "longitude": 139.52118055555556,
            "model": "iPhone 14 Pro Max back dual wide camera 6.86mm f/1.78",
            "make": "Apple",
            "time": "2023-05-18T10:34:00.000Z"
        },
        {
            "original": "contents/20230518/original/IMG_2638.avif",
            "thumbnail": "contents/20230518/thumbnail/IMG_2638.avif",
            "desc": "",
            "latitude": 36.31442222222222,
            "longitude": 139.52120833333333,
            "model": "iPhone 14 Pro Max back triple camera 6.86mm f/1.78",
            "make": "Apple",
            "time": "2023-05-18T10:34:27.000Z"
        },
        {
            "original": "contents/20230518/original/IMG_2639.avif",
            "thumbnail": "contents/20230518/thumbnail/IMG_2639.avif",
            "desc": "",
            "latitude": 36.314413888888886,
            "longitude": 139.52119444444446,
            "model": "iPhone 14 Pro Max back triple camera 6.86mm f/1.78",
            "make": "Apple",
            "time": "2023-05-18T10:35:01.000Z"
        },
        {
            "original": "contents/20230518/original/IMG_2640.avif",
            "thumbnail": "contents/20230518/thumbnail/IMG_2640.avif",
            "desc": "",
            "latitude": 36.313988888888886,
            "longitude": 139.5208888888889,
            "model": "iPhone 14 Pro Max back dual camera 9mm f/2.8",
            "make": "Apple",
            "time": "2023-05-18T10:40:56.000Z"
        },
        {
            "original": "contents/20230518/original/IMG_2641.avif",
            "thumbnail": "contents/20230518/thumbnail/IMG_2641.avif",
            "desc": "",
            "latitude": 36.31388611111111,
            "longitude": 139.52082777777778,
            "model": "iPhone 14 Pro Max back dual camera 9mm f/2.8",
            "make": "Apple",
            "time": "2023-05-18T10:42:30.000Z"
        },
        {
            "original": "contents/20230518/original/IMG_2643.avif",
            "thumbnail": "contents/20230518/thumbnail/IMG_2643.avif",
            "desc": "",
            "latitude": 36.313775,
            "longitude": 139.52064444444446,
            "model": "iPhone 14 Pro Max back triple camera 6.86mm f/1.78",
            "make": "Apple",
            "time": "2023-05-18T10:43:22.000Z"
        },
        {
            "original": "contents/20230518/original/IMG_2644.avif",
            "thumbnail": "contents/20230518/thumbnail/IMG_2644.avif",
            "desc": "",
            "latitude": 36.31374444444444,
            "longitude": 139.52036944444447,
            "model": "iPhone 14 Pro Max back triple camera 6.86mm f/1.78",
            "make": "Apple",
            "time": "2023-05-18T10:44:08.000Z"
        },
        {
            "original": "contents/20230518/original/IMG_2645.avif",
            "thumbnail": "contents/20230518/thumbnail/IMG_2645.avif",
            "desc": "",
            "latitude": 36.31377777777777,
            "longitude": 139.520325,
            "model": "iPhone 14 Pro Max back dual camera 9mm f/2.8",
            "make": "Apple",
            "time": "2023-05-18T10:44:33.000Z"
        },
        {
            "original": "contents/20230518/original/IMG_2646.avif",
            "thumbnail": "contents/20230518/thumbnail/IMG_2646.avif",
            "desc": "",
            "latitude": 36.31375833333333,
            "longitude": 139.52015555555556,
            "model": "iPhone 14 Pro Max back dual wide camera 6.86mm f/1.78",
            "make": "Apple",
            "time": "2023-05-18T10:45:02.000Z"
        },
        {
            "original": "contents/20230518/original/IMG_2647.avif",
            "thumbnail": "contents/20230518/thumbnail/IMG_2647.avif",
            "desc": "",
            "latitude": 36.31378888888889,
            "longitude": 139.520125,
            "model": "iPhone 14 Pro Max back dual wide camera 6.86mm f/1.78",
            "make": "Apple",
            "time": "2023-05-18T10:45:20.000Z"
        },
        {
            "original": "contents/20230518/original/IMG_2648.avif",
            "thumbnail": "contents/20230518/thumbnail/IMG_2648.avif",
            "desc": "",
            "latitude": 36.31393055555555,
            "longitude": 139.52023333333335,
            "model": "iPhone 14 Pro Max back dual camera 9mm f/2.8",
            "make": "Apple",
            "time": "2023-05-18T10:46:06.000Z"
        },
        {
            "original": "contents/20230518/original/IMG_2649.avif",
            "thumbnail": "contents/20230518/thumbnail/IMG_2649.avif",
            "desc": "",
            "latitude": 36.31396944444444,
            "longitude": 139.52023333333335,
            "model": "iPhone 14 Pro Max back dual camera 9mm f/2.8",
            "make": "Apple",
            "time": "2023-05-18T10:46:30.000Z"
        },
        {
            "original": "contents/20230518/original/IMG_2650.avif",
            "thumbnail": "contents/20230518/thumbnail/IMG_2650.avif",
            "desc": "",
            "latitude": 36.31376944444444,
            "longitude": 139.520125,
            "model": "iPhone 14 Pro Max back dual camera 9mm f/2.8",
            "make": "Apple",
            "time": "2023-05-18T10:47:48.000Z"
        },
        {
            "original": "contents/20230518/original/IMG_2651.avif",
            "thumbnail": "contents/20230518/thumbnail/IMG_2651.avif",
            "desc": "",
            "latitude": 36.31374722222222,
            "longitude": 139.52001944444447,
            "model": "iPhone 14 Pro Max back triple camera 6.86mm f/1.78",
            "make": "Apple",
            "time": "2023-05-18T10:48:19.000Z"
        },
        {
            "original": "contents/20230518/original/IMG_2652.avif",
            "thumbnail": "contents/20230518/thumbnail/IMG_2652.avif",
            "desc": "",
            "latitude": 36.31370277777778,
            "longitude": 139.51995833333334,
            "model": "iPhone 14 Pro Max back triple camera 6.86mm f/1.78",
            "make": "Apple",
            "time": "2023-05-18T10:48:47.000Z"
        },
        {
            "original": "contents/20230518/original/IMG_2653.avif",
            "thumbnail": "contents/20230518/thumbnail/IMG_2653.avif",
            "desc": "",
            "latitude": 36.31368888888888,
            "longitude": 139.52000555555557,
            "model": "iPhone 14 Pro Max back dual camera 9mm f/2.8",
            "make": "Apple",
            "time": "2023-05-18T10:49:42.000Z"
        },
        {
            "original": "contents/20230518/original/IMG_2655.avif",
            "thumbnail": "contents/20230518/thumbnail/IMG_2655.avif",
            "desc": "",
            "latitude": 36.31370833333333,
            "longitude": 139.51946944444447,
            "model": "iPhone 14 Pro Max back dual camera 9mm f/2.8",
            "make": "Apple",
            "time": "2023-05-18T11:09:31.000Z"
        },
        {
            "original": "contents/20230518/original/IMG_2656.avif",
            "thumbnail": "contents/20230518/thumbnail/IMG_2656.avif",
            "desc": "",
            "latitude": 36.313716666666664,
            "longitude": 139.5194388888889,
            "model": "iPhone 14 Pro Max back dual camera 9mm f/2.8",
            "make": "Apple",
            "time": "2023-05-18T11:09:43.000Z"
        },
        {
            "original": "contents/20230518/original/IMG_2657.avif",
            "thumbnail": "contents/20230518/thumbnail/IMG_2657.avif",
            "desc": "",
            "latitude": 36.313491666666664,
            "longitude": 139.5193777777778,
            "model": "iPhone 14 Pro Max back triple camera 6.86mm f/1.78",
            "make": "Apple",
            "time": "2023-05-18T11:10:15.000Z"
        },
        {
            "original": "contents/20230518/original/IMG_2658.avif",
            "thumbnail": "contents/20230518/thumbnail/IMG_2658.avif",
            "desc": "",
            "latitude": 36.313116666666666,
            "longitude": 139.51934722222222,
            "model": "iPhone 14 Pro Max back triple camera 6.86mm f/1.78",
            "make": "Apple",
            "time": "2023-05-18T11:11:20.000Z"
        },
        {
            "original": "contents/20230518/original/IMG_2660.avif",
            "thumbnail": "contents/20230518/thumbnail/IMG_2660.avif",
            "desc": "",
            "latitude": 36.31296111111111,
            "longitude": 139.51905833333333,
            "model": "iPhone 14 Pro Max back dual wide camera 6.86mm f/1.78",
            "make": "Apple",
            "time": "2023-05-18T11:14:33.000Z"
        },
        {
            "original": "contents/20230518/original/IMG_2661.avif",
            "thumbnail": "contents/20230518/thumbnail/IMG_2661.avif",
            "desc": "",
            "latitude": 36.31308333333333,
            "longitude": 139.51899722222223,
            "model": "iPhone 14 Pro Max back triple camera 6.86mm f/1.78",
            "make": "Apple",
            "time": "2023-05-18T11:15:04.000Z"
        },
        {
            "original": "contents/20230518/original/IMG_2662.avif",
            "thumbnail": "contents/20230518/thumbnail/IMG_2662.avif",
            "desc": "",
            "latitude": 36.313849999999995,
            "longitude": 139.51880000000003,
            "model": "iPhone 14 Pro Max back triple camera 6.86mm f/1.78",
            "make": "Apple",
            "time": "2023-05-18T11:17:14.000Z"
        },
        {
            "original": "contents/20230518/original/IMG_2663.avif",
            "thumbnail": "contents/20230518/thumbnail/IMG_2663.avif",
            "desc": "",
            "latitude": 36.31388888888888,
            "longitude": 139.5187527777778,
            "model": "iPhone 14 Pro Max back dual wide camera 6.86mm f/1.78",
            "make": "Apple",
            "time": "2023-05-18T11:17:32.000Z"
        },
        {
            "original": "contents/20230518/original/IMG_2664.avif",
            "thumbnail": "contents/20230518/thumbnail/IMG_2664.avif",
            "desc": "",
            "latitude": 36.314391666666666,
            "longitude": 139.51918055555558,
            "model": "iPhone 14 Pro Max back triple camera 6.86mm f/1.78",
            "make": "Apple",
            "time": "2023-05-18T11:19:14.000Z"
        },
        {
            "original": "contents/20230518/original/IMG_2665.avif",
            "thumbnail": "contents/20230518/thumbnail/IMG_2665.avif",
            "desc": "",
            "latitude": 36.31446944444444,
            "longitude": 139.51946944444447,
            "model": "iPhone 14 Pro Max back triple camera 6.86mm f/1.78",
            "make": "Apple",
            "time": "2023-05-18T11:20:05.000Z"
        },
        {
            "original": "contents/20230518/original/IMG_2666.avif",
            "thumbnail": "contents/20230518/thumbnail/IMG_2666.avif",
            "desc": "",
            "latitude": 36.31481944444444,
            "longitude": 139.51974444444446,
            "model": "iPhone 14 Pro Max back triple camera 6.86mm f/1.78",
            "make": "Apple",
            "time": "2023-05-18T11:21:19.000Z"
        },
        {
            "original": "contents/20230518/original/IMG_2667.avif",
            "thumbnail": "contents/20230518/thumbnail/IMG_2667.avif",
            "desc": "",
            "latitude": 36.31482222222222,
            "longitude": 139.51976111111114,
            "model": "iPhone 14 Pro Max back triple camera 6.86mm f/1.78",
            "make": "Apple",
            "time": "2023-05-18T11:21:36.000Z"
        },
        {
            "original": "contents/20230518/original/IMG_2669.avif",
            "thumbnail": "contents/20230518/thumbnail/IMG_2669.avif",
            "desc": "",
            "latitude": 36.31489444444444,
            "longitude": 139.51994444444446,
            "model": "iPhone 14 Pro Max back triple camera 6.86mm f/1.78",
            "make": "Apple",
            "time": "2023-05-18T11:22:19.000Z"
        },
        {
            "original": "contents/20230518/original/IMG_2670.avif",
            "thumbnail": "contents/20230518/thumbnail/IMG_2670.avif",
            "desc": "",
            "latitude": 36.31483333333333,
            "longitude": 139.52005000000003,
            "model": "iPhone 14 Pro Max back dual wide camera 6.86mm f/1.78",
            "make": "Apple",
            "time": "2023-05-18T11:26:09.000Z"
        },
        {
            "original": "contents/20230518/original/IMG_2671.avif",
            "thumbnail": "contents/20230518/thumbnail/IMG_2671.avif",
            "desc": "",
            "latitude": 36.3148,
            "longitude": 139.520325,
            "model": "iPhone 14 Pro Max back dual wide camera 6.86mm f/1.78",
            "make": "Apple",
            "time": "2023-05-18T11:27:00.000Z"
        },
        {
            "original": "contents/20230518/original/IMG_2672.avif",
            "thumbnail": "contents/20230518/thumbnail/IMG_2672.avif",
            "desc": "",
            "latitude": 36.314880555555554,
            "longitude": 139.52046111111113,
            "model": "iPhone 14 Pro Max back triple camera 6.86mm f/1.78",
            "make": "Apple",
            "time": "2023-05-18T11:28:18.000Z"
        },
        {
            "original": "contents/20230518/original/IMG_2673.avif",
            "thumbnail": "contents/20230518/thumbnail/IMG_2673.avif",
            "desc": "",
            "latitude": 36.314788888888884,
            "longitude": 139.5208138888889,
            "model": "iPhone 14 Pro Max back dual wide camera 6.86mm f/1.78",
            "make": "Apple",
            "time": "2023-05-18T11:29:31.000Z"
        },
        {
            "original": "contents/20230518/original/IMG_2674.avif",
            "thumbnail": "contents/20230518/thumbnail/IMG_2674.avif",
            "desc": "",
            "latitude": 36.314791666666665,
            "longitude": 139.52098055555558,
            "model": "iPhone 14 Pro Max back triple camera 6.86mm f/1.78",
            "make": "Apple",
            "time": "2023-05-18T11:29:58.000Z"
        },
        {
            "original": "contents/20230518/original/IMG_2675.avif",
            "thumbnail": "contents/20230518/thumbnail/IMG_2675.avif",
            "desc": "",
            "latitude": 36.31475555555555,
            "longitude": 139.5214527777778,
            "model": "iPhone 14 Pro Max back dual wide camera 6.86mm f/1.78",
            "make": "Apple",
            "time": "2023-05-18T11:31:09.000Z"
        },
        {
            "original": "contents/20230518/original/IMG_2676.avif",
            "thumbnail": "contents/20230518/thumbnail/IMG_2676.avif",
            "desc": "점심ㄴ",
            "latitude": 36.32196944444445,
            "longitude": 139.57698055555556,
            "model": "iPhone 14 Pro Max back triple camera 6.86mm f/1.78",
            "make": "Apple",
            "time": "2023-05-18T12:32:34.000Z"
        },
        {
            "original": "contents/20230518/original/IMG_2677.avif",
            "thumbnail": "contents/20230518/thumbnail/IMG_2677.avif",
            "desc": "",
            "latitude": 36.32037777777778,
            "longitude": 139.57374444444443,
            "model": "iPhone 14 Pro Max back triple camera 6.86mm f/1.78",
            "make": "Apple",
            "time": "2023-05-18T12:56:12.000Z"
        },
        {
            "original": "contents/20230518/original/IMG_2678.avif",
            "thumbnail": "contents/20230518/thumbnail/IMG_2678.avif",
            "desc": "",
            "latitude": 36.32040277777778,
            "longitude": 139.5737611111111,
            "model": "iPhone 14 Pro Max back triple camera 6.86mm f/1.78",
            "make": "Apple",
            "time": "2023-05-18T12:56:15.000Z"
        },
        {
            "original": "contents/20230518/original/IMG_2679.avif",
            "thumbnail": "contents/20230518/thumbnail/IMG_2679.avif",
            "desc": "",
            "latitude": 36.32087222222223,
            "longitude": 139.57401944444445,
            "model": "iPhone 14 Pro Max back triple camera 6.86mm f/1.78",
            "make": "Apple",
            "time": "2023-05-18T12:58:09.000Z"
        },
        {
            "original": "contents/20230518/original/IMG_2680.avif",
            "thumbnail": "contents/20230518/thumbnail/IMG_2680.avif",
            "desc": "",
            "latitude": 36.31563055555555,
            "longitude": 139.57623333333333,
            "model": "iPhone 14 Pro Max back triple camera 9mm f/2.8",
            "make": "Apple",
            "time": "2023-05-18T13:12:48.000Z"
        },
        {
            "original": "contents/20230518/original/IMG_2681.avif",
            "thumbnail": "contents/20230518/thumbnail/IMG_2681.avif",
            "desc": "작업할 목적으로 들른 스타벅스. 근처에 학교가 많아서 그런지 학생들이 엄청 많음",
            "latitude": 36.37851666666667,
            "longitude": 139.73315555555556,
            "model": "iPhone 14 Pro Max back triple camera 6.86mm f/1.78",
            "make": "Apple",
            "time": "2023-05-18T15:27:19.000Z"
        },
        {
            "original": "contents/20230518/original/IMG_2683.avif",
            "thumbnail": "contents/20230518/thumbnail/IMG_2683.avif",
            "desc": "",
            "latitude": 36.37852222222222,
            "longitude": 139.73323055555556,
            "model": "iPhone 14 Pro Max back triple camera 6.86mm f/1.78",
            "make": "Apple",
            "time": "2023-05-18T16:39:43.000Z"
        },
        {
            "original": "contents/20230518/original/IMG_2684.avif",
            "thumbnail": "contents/20230518/thumbnail/IMG_2684.avif",
            "desc": "",
            "latitude": 36.376552777777775,
            "longitude": 139.73129166666666,
            "model": "iPhone 14 Pro Max back triple camera 6.86mm f/1.78",
            "make": "Apple",
            "time": "2023-05-18T18:07:27.000Z"
        }
    ]
}